termflow/__init__.py
termflow/main.py
termflow/core/__init__.py
termflow/data/HELP.md
termflow/data/INFO.md
termflow/data/__init__.py
termflow/data/config.toml
termflow/data/styles.tcss
termflow/data/todos.json
termflow/panels/__init__.py
termflow/panels/clock.py
termflow/panels/info.py
termflow/panels/pomodoro.py
termflow/panels/todo.py
termflow/panels/todo_list.py
termflow/ui/__init__.py
termflow/ui/app.py
termflow/ui/styles.tcss
termflow/utils/__init__.py
termflow/utils/open_docs.py
termflow/utils/quotes.py
termflow/utils/resources.py
termflow/utils/storage.py
termflow/utils/todos.py
termflow/utils/weather.py
termflow_cli-0.1.4.dist-info/METADATA
termflow_cli-0.1.4.dist-info/WHEEL
termflow_cli-0.1.4.dist-info/entry_points.txt
termflow_cli-0.1.4.dist-info/top_level.txt
termflow_cli-0.1.4.dist-info/RECORD
