Metadata-Version: 2.4
Name: termflow-cli
Version: 0.1.4
Summary: A minimalist terminal productivity hub built with Textual
Requires-Python: >=3.10
Requires-Dist: textual
Requires-Dist: platformdirs>=4.5.1
Requires-Dist: requests>=2.32.5
Requires-Dist: rich>=14.2.0
Requires-Dist: tomli>=2.4.0
Requires-Dist: tomli-w>=1.2.0
